{
  "step": 0,
  "metrics": {
    "step": 0,
    "stage": "Stage1",
    "losses": {
      "primary": {
        "objective_name": "conditioned_denoising",
        "primary_value": 14.67241096496582,
        "decoder_anchored": true
      },
      "auxiliaries": {
        "intra_red": 3.0381860733032227,
        "probe": 4.956212043762207,
        "leak": 0.0,
        "gate": 0.5626429915428162,
        "slot": 0.13208507001399994,
        "consistency": 0.19275476038455963,
        "pocket_contact": 0.6844226121902466,
        "pocket_clash": 0.0
      },
      "total": 14.691686630249023
    }
  },
  "config_hash": "f490bd8602a2ec9e",
  "dataset_validation_fingerprint": "c42e04afc454980c",
  "metric_schema_version": 5,
  "resume_contract_version": "weights+history+step",
  "optimizer_state": {
    "optimizer_kind": "adam",
    "learning_rate": 0.001,
    "weight_decay": 0.0,
    "internal_state_persisted": false
  },
  "scheduler_state": {
    "stage": "Stage1",
    "primary_weight": 1.0,
    "intra_red_weight": 0.0,
    "probe_weight": 0.0,
    "leak_weight": 0.0,
    "gate_weight": 0.0,
    "slot_weight": 0.0,
    "consistency_weight": 0.1,
    "pocket_contact_weight": 0.0,
    "pocket_clash_weight": 0.0
  }
}